hello_world.py
helloworld2025-0.0.1.dist-info/licenses/LICENSE.txt
helloworld2025-0.0.1.dist-info/METADATA
helloworld2025-0.0.1.dist-info/WHEEL
helloworld2025-0.0.1.dist-info/top_level.txt
helloworld2025-0.0.1.dist-info/RECORD
